{
  "sensor1": {
    "isRoot": true,
    "isSensorOn": true,
    "isLampOn": false,
    "bypassMode": -1,
    "neighbor": [
      "sensor2",
      "sensor3"
    ],
    "other": [
      "sensor4",
      "sensor5",
      "sensor6"
    ]
  },
  "sensor2": {
    "isRoot": false,
    "isSensorOn": false,
    "isLampOn": false,
    "bypassMode": -1,
    "neighbor": [
      "sensor1",
      "sensor3",
      "sensor4",
      "sensor5",
      "sensor6"
    ],
    "other": []
  },
  "sensor3": {
    "isRoot": false,
    "isSensorOn": false,
    "isLampOn": false,
    "bypassMode": -1,
    "neighbor": [
      "sensor1",
      "sensor2"
    ],
    "other": [
      "sensor4",
      "sensor5",
      "sensor6"
    ]
  },
  "sensor4": {
    "isRoot": false,
    "isSensorOn": false,
    "isLampOn": false,
    "bypassMode": -1,
    "neighbor": [
      "sensor2",
      "sensor5",
      "sensor6"
    ],
    "other": [
      "sensor1",
      "sensor3"
    ]
  },
  "sensor5": {
    "isRoot": false,
    "isSensorOn": false,
    "isLampOn": false,
    "bypassMode": -1,
    "neighbor": [
      "sensor2",
      "sensor4",
      "sensor6"
    ],
    "other": [
      "sensor1",
      "sensor3"
    ]
  },
  "sensor6": {
    "isRoot": false,
    "isSensorOn": false,
    "isLampOn": false,
    "bypassMode": -1,
    "neighbor": [
      "sensor2",
      "sensor4",
      "sensor5"
    ],
    "other": [
      "sensor1",
      "sensor3"
    ]
  }
}